__init__.py
multilogue/__init__.py
multilogue/conversations.py
multilogue/entities.py
multilogue/participants.py
multilogue/utilities/__init__.py
multilogue/utilities/chatgpt.py
multilogue/utilities/exceptions.py
multilogue/utilities/functions.py
multilogue/utilities/githublog.py
multilogue-0.0.15.dist-info/LICENSE
multilogue-0.0.15.dist-info/METADATA
multilogue-0.0.15.dist-info/WHEEL
multilogue-0.0.15.dist-info/top_level.txt
multilogue-0.0.15.dist-info/RECORD
